NiukeJavaGongchengshiQiuzhiJingyanFenxiang20212022/README.md
NiukeJavaGongchengshiQiuzhiJingyanFenxiang20212022/__init__.py
NiukeJavaGongchengshiQiuzhiJingyanFenxiang20212022/__main__.py
NiukeJavaGongchengshiQiuzhiJingyanFenxiang20212022/file.epub
NiukeJavaGongchengshiQiuzhiJingyanFenxiang20212022/index.html
NiukeJavaGongchengshiQiuzhiJingyanFenxiang20212022/css/__init__.py
NiukeJavaGongchengshiQiuzhiJingyanFenxiang20212022/css/annotations.css
NiukeJavaGongchengshiQiuzhiJingyanFenxiang20212022/css/main.css
NiukeJavaGongchengshiQiuzhiJingyanFenxiang20212022/css/normalize.css
NiukeJavaGongchengshiQiuzhiJingyanFenxiang20212022/css/popup.css
NiukeJavaGongchengshiQiuzhiJingyanFenxiang20212022/font/__init__.py
NiukeJavaGongchengshiQiuzhiJingyanFenxiang20212022/font/fontello.eot
NiukeJavaGongchengshiQiuzhiJingyanFenxiang20212022/font/fontello.svg
NiukeJavaGongchengshiQiuzhiJingyanFenxiang20212022/font/fontello.ttf
NiukeJavaGongchengshiQiuzhiJingyanFenxiang20212022/font/fontello.woff
NiukeJavaGongchengshiQiuzhiJingyanFenxiang20212022/img/__init__.py
NiukeJavaGongchengshiQiuzhiJingyanFenxiang20212022/img/annotator-glyph-sprite.png
NiukeJavaGongchengshiQiuzhiJingyanFenxiang20212022/img/annotator-icon-sprite.png
NiukeJavaGongchengshiQiuzhiJingyanFenxiang20212022/img/apple-touch-icon.png
NiukeJavaGongchengshiQiuzhiJingyanFenxiang20212022/img/cancelfullscreen.png
NiukeJavaGongchengshiQiuzhiJingyanFenxiang20212022/img/close.png
NiukeJavaGongchengshiQiuzhiJingyanFenxiang20212022/img/fullscreen.png
NiukeJavaGongchengshiQiuzhiJingyanFenxiang20212022/img/loader.gif
NiukeJavaGongchengshiQiuzhiJingyanFenxiang20212022/img/menu-icon.png
NiukeJavaGongchengshiQiuzhiJingyanFenxiang20212022/img/save.png
NiukeJavaGongchengshiQiuzhiJingyanFenxiang20212022/img/saved.png
NiukeJavaGongchengshiQiuzhiJingyanFenxiang20212022/img/settings-s.png
NiukeJavaGongchengshiQiuzhiJingyanFenxiang20212022/img/settings.png
NiukeJavaGongchengshiQiuzhiJingyanFenxiang20212022/img/star.png
niuke_java_gongchengshi_qiuzhi_jingyan_fenxiang_2021_2022-2024.3.6.0.dist-info/METADATA
niuke_java_gongchengshi_qiuzhi_jingyan_fenxiang_2021_2022-2024.3.6.0.dist-info/WHEEL
niuke_java_gongchengshi_qiuzhi_jingyan_fenxiang_2021_2022-2024.3.6.0.dist-info/entry_points.txt
niuke_java_gongchengshi_qiuzhi_jingyan_fenxiang_2021_2022-2024.3.6.0.dist-info/top_level.txt
niuke_java_gongchengshi_qiuzhi_jingyan_fenxiang_2021_2022-2024.3.6.0.dist-info/RECORD
